<?xml version="1.0" encoding="UTF-8"?>
<!--oriflamms data file-->
<OriData>
    <validation>
        <v id="w_inscriptions_12354" ok="2" left="0" right="0" imgsig=""/>
        <v id="pc_inscriptions_12327" ok="2" left="0" right="0" imgsig=""/>
        <v id="w_p_w_inscriptions_12367_2" ok="2" left="0" right="0" imgsig=""/>
        <v id="w_inscriptions_12325" ok="2" left="0" right="0" imgsig=""/>
        <v id="w_p_w_inscriptions_12367_1" ok="2" left="0" right="0" imgsig=""/>
        <v id="w_inscriptions_12326" ok="2" left="0" right="0" imgsig=""/>
        <v id="w_inscriptions_12328" ok="2" left="0" right="0" imgsig=""/>
        <v id="w_inscriptions_12377" ok="2" left="0" right="0" imgsig=""/>
        <v id="pc_inscriptions_12357" ok="2" left="0" right="0" imgsig=""/>
        <v id="w_inscriptions_12333" ok="2" left="0" right="0" imgsig=""/>
        <v id="w_inscriptions_12381" ok="2" left="0" right="0" imgsig=""/>
        <v id="w_inscriptions_12330" ok="2" left="0" right="0" imgsig=""/>
        <v id="pc_inscriptions_12329" ok="2" left="0" right="0" imgsig=""/>
        <v id="w_p_w_inscriptions_12359_2" ok="2" left="0" right="0" imgsig=""/>
        <v id="w_inscriptions_12380" ok="2" left="0" right="0" imgsig=""/>
        <v id="w_inscriptions_12331" ok="2" left="0" right="0" imgsig=""/>
        <v id="pc_inscriptions_12332" ok="2" left="0" right="0" imgsig=""/>
        <v id="w_inscriptions_12385" ok="2" left="0" right="0" imgsig=""/>
        <v id="w_inscriptions_12334" ok="2" left="0" right="0" imgsig=""/>
        <v id="w_inscriptions_12335" ok="2" left="0" right="0" imgsig=""/>
        <v id="w_inscriptions_12336" ok="2" left="0" right="0" imgsig=""/>
        <v id="w_inscriptions_12337" ok="2" left="0" right="0" imgsig=""/>
        <v id="w_inscriptions_12338" ok="2" left="0" right="0" imgsig=""/>
        <v id="w_inscriptions_12339" ok="2" left="0" right="0" imgsig=""/>
        <v id="w_inscriptions_12360" ok="2" left="0" right="0" imgsig=""/>
        <v id="pc_inscriptions_12340" ok="2" left="0" right="0" imgsig=""/>
        <v id="w_inscriptions_12341" ok="2" left="0" right="0" imgsig=""/>
        <v id="w_inscriptions_12342" ok="2" left="0" right="0" imgsig=""/>
        <v id="pc_inscriptions_12363" ok="2" left="0" right="0" imgsig=""/>
        <v id="w_inscriptions_12343" ok="2" left="0" right="0" imgsig=""/>
        <v id="w_inscriptions_12344" ok="2" left="0" right="0" imgsig=""/>
        <v id="w_inscriptions_12365" ok="2" left="0" right="0" imgsig=""/>
        <v id="pc_inscriptions_12345" ok="2" left="0" right="0" imgsig=""/>
        <v id="w_inscriptions_12346" ok="2" left="0" right="0" imgsig=""/>
        <v id="pc_inscriptions_12379" ok="2" left="0" right="0" imgsig=""/>
        <v id="w_p_w_inscriptions_12347_1" ok="2" left="0" right="0" imgsig=""/>
        <v id="w_p_w_inscriptions_12347_2" ok="2" left="0" right="0" imgsig=""/>
        <v id="w_inscriptions_12368" ok="2" left="0" right="0" imgsig=""/>
        <v id="pc_inscriptions_12348" ok="2" left="0" right="0" imgsig=""/>
        <v id="pc_inscriptions_12369" ok="2" left="0" right="0" imgsig=""/>
        <v id="w_inscriptions_12356" ok="2" left="0" right="0" imgsig=""/>
        <v id="w_inscriptions_12349" ok="2" left="0" right="0" imgsig=""/>
        <v id="w_inscriptions_12350" ok="2" left="0" right="0" imgsig=""/>
        <v id="w_inscriptions_12371" ok="2" left="0" right="0" imgsig=""/>
        <v id="pc_inscriptions_12351" ok="2" left="0" right="0" imgsig=""/>
        <v id="w_inscriptions_12352" ok="2" left="0" right="0" imgsig=""/>
        <v id="pc_inscriptions_12382" ok="2" left="0" right="0" imgsig=""/>
        <v id="pc_inscriptions_12373" ok="2" left="0" right="0" imgsig=""/>
        <v id="w_inscriptions_12353" ok="2" left="0" right="0" imgsig=""/>
        <v id="w_inscriptions_12375" ok="2" left="0" right="0" imgsig=""/>
        <v id="pc_inscriptions_12355" ok="2" left="0" right="0" imgsig=""/>
        <v id="w_inscriptions_12358" ok="2" left="0" right="0" imgsig=""/>
        <v id="w_p_w_inscriptions_12359_1" ok="2" left="0" right="0" imgsig=""/>
        <v id="w_inscriptions_12383" ok="2" left="0" right="0" imgsig=""/>
        <v id="w_inscriptions_12361" ok="2" left="0" right="0" imgsig=""/>
        <v id="w_inscriptions_12362" ok="2" left="0" right="0" imgsig=""/>
        <v id="w_inscriptions_12364" ok="2" left="0" right="0" imgsig=""/>
        <v id="w_inscriptions_12366" ok="2" left="0" right="0" imgsig=""/>
        <v id="w_inscriptions_12370" ok="2" left="0" right="0" imgsig=""/>
        <v id="w_inscriptions_12372" ok="2" left="0" right="0" imgsig=""/>
        <v id="w_inscriptions_12374" ok="2" left="0" right="0" imgsig=""/>
        <v id="w_p_w_inscriptions_12376_1" ok="2" left="0" right="0" imgsig=""/>
        <v id="w_p_w_inscriptions_12403_1" ok="2" left="0" right="0" imgsig=""/>
        <v id="w_inscriptions_12378" ok="2" left="0" right="0" imgsig=""/>
        <v id="w_p_w_inscriptions_12376_2" ok="2" left="0" right="0" imgsig=""/>
        <v id="pc_inscriptions_12384" ok="2" left="0" right="0" imgsig=""/>
        <v id="w_inscriptions_12386" ok="2" left="0" right="0" imgsig=""/>
        <v id="w_inscriptions_12387" ok="2" left="0" right="0" imgsig=""/>
        <v id="w_inscriptions_12388" ok="2" left="0" right="0" imgsig=""/>
        <v id="w_inscriptions_12389" ok="2" left="0" right="0" imgsig=""/>
        <v id="pc_inscriptions_12390" ok="2" left="0" right="0" imgsig=""/>
        <v id="w_inscriptions_12391" ok="2" left="0" right="0" imgsig=""/>
        <v id="w_inscriptions_12392" ok="2" left="0" right="0" imgsig=""/>
        <v id="pc_inscriptions_12393" ok="2" left="0" right="0" imgsig=""/>
        <v id="w_inscriptions_12394" ok="2" left="0" right="0" imgsig=""/>
        <v id="w_inscriptions_12395" ok="2" left="0" right="0" imgsig=""/>
        <v id="w_inscriptions_12396" ok="2" left="0" right="0" imgsig=""/>
        <v id="w_p_w_inscriptions_12397_1" ok="2" left="0" right="0" imgsig=""/>
        <v id="w_p_w_inscriptions_12397_2" ok="2" left="0" right="0" imgsig=""/>
        <v id="w_inscriptions_12398" ok="2" left="0" right="0" imgsig=""/>
        <v id="pc_inscriptions_12399" ok="2" left="0" right="0" imgsig=""/>
        <v id="w_inscriptions_12400" ok="2" left="0" right="0" imgsig=""/>
        <v id="w_inscriptions_12401" ok="2" left="0" right="0" imgsig=""/>
        <v id="w_inscriptions_12402" ok="2" left="0" right="0" imgsig=""/>
        <v id="w_p_w_inscriptions_12403_2" ok="2" left="0" right="0" imgsig=""/>
        <v id="w_inscriptions_12404" ok="2" left="0" right="0" imgsig=""/>
        <v id="w_inscriptions_12405" ok="2" left="0" right="0" imgsig=""/>
        <v id="w_inscriptions_12406" ok="2" left="0" right="0" imgsig=""/>
        <v id="pc_inscriptions_12407" ok="2" left="0" right="0" imgsig=""/>
        <v id="w_inscriptions_12408" ok="2" left="0" right="0" imgsig=""/>
        <v id="w_inscriptions_12409" ok="2" left="0" right="0" imgsig=""/>
        <v id="w_inscriptions_12410" ok="2" left="0" right="0" imgsig=""/>
    </validation>
    <medlines>
        <column id="col_inscriptions_468_1">
            <GraphicalLine lh="22">
                <LinearInterpolation>
                    <Point2DDouble x="2643" y="392"/>
                    <Point2DDouble x="2970" y="392"/>
                    <Point2DDouble x="3000" y="395"/>
                    <Point2DDouble x="3090" y="415"/>
                    <Point2DDouble x="3170" y="416"/>
                    <Point2DDouble x="3205" y="417"/>
                </LinearInterpolation>
            </GraphicalLine>
            <GraphicalLine lh="22">
                <LinearInterpolation>
                    <Point2DDouble x="2937" y="771"/>
                    <Point2DDouble x="2970" y="771"/>
                    <Point2DDouble x="3080" y="770"/>
                    <Point2DDouble x="3123" y="769"/>
                </LinearInterpolation>
            </GraphicalLine>
            <GraphicalLine lh="22">
                <LinearInterpolation>
                    <Point2DDouble x="2940" y="799"/>
                    <Point2DDouble x="3114" y="799"/>
                </LinearInterpolation>
            </GraphicalLine>
            <GraphicalLine lh="22">
                <LinearInterpolation>
                    <Point2DDouble x="2776" y="979"/>
                    <Point2DDouble x="3130" y="979"/>
                    <Point2DDouble x="3179" y="978"/>
                </LinearInterpolation>
            </GraphicalLine>
            <GraphicalLine lh="22">
                <LinearInterpolation>
                    <Point2DDouble x="2596" y="1088"/>
                    <Point2DDouble x="3070" y="1088"/>
                    <Point2DDouble x="3090" y="1077"/>
                    <Point2DDouble x="3110" y="1077"/>
                    <Point2DDouble x="3180" y="1076"/>
                </LinearInterpolation>
            </GraphicalLine>
            <GraphicalLine lh="22">
                <LinearInterpolation>
                    <Point2DDouble x="2808" y="1227"/>
                    <Point2DDouble x="2910" y="1227"/>
                    <Point2DDouble x="2950" y="1228"/>
                    <Point2DDouble x="2990" y="1229"/>
                    <Point2DDouble x="3050" y="1230"/>
                    <Point2DDouble x="3148" y="1231"/>
                </LinearInterpolation>
            </GraphicalLine>
            <GraphicalLine lh="22">
                <LinearInterpolation>
                    <Point2DDouble x="2847" y="1291"/>
                    <Point2DDouble x="2980" y="1291"/>
                    <Point2DDouble x="3050" y="1292"/>
                    <Point2DDouble x="3104" y="1293"/>
                </LinearInterpolation>
            </GraphicalLine>
            <GraphicalLine lh="22">
                <LinearInterpolation>
                    <Point2DDouble x="2919" y="1553"/>
                    <Point2DDouble x="3252" y="1553"/>
                </LinearInterpolation>
            </GraphicalLine>
            <GraphicalLine lh="22">
                <LinearInterpolation>
                    <Point2DDouble x="2952" y="1694"/>
                    <Point2DDouble x="3020" y="1694"/>
                    <Point2DDouble x="3149" y="1709"/>
                </LinearInterpolation>
            </GraphicalLine>
        </column>
    </medlines>
    <lineLinks>
        <ll id="line_inscriptions_468_1_1" col="col_inscriptions_468_1" n="0"/>
        <ll id="line_inscriptions_468_1_9" col="col_inscriptions_468_1" n="8"/>
        <ll id="line_inscriptions_468_1_2" col="col_inscriptions_468_1" n="1"/>
        <ll id="line_inscriptions_468_1_3" col="col_inscriptions_468_1" n="2"/>
        <ll id="line_inscriptions_468_1_4" col="col_inscriptions_468_1" n="3"/>
        <ll id="line_inscriptions_468_1_5" col="col_inscriptions_468_1" n="4"/>
        <ll id="line_inscriptions_468_1_6" col="col_inscriptions_468_1" n="5"/>
        <ll id="line_inscriptions_468_1_7" col="col_inscriptions_468_1" n="6"/>
        <ll id="line_inscriptions_468_1_8" col="col_inscriptions_468_1" n="7"/>
    </lineLinks>
</OriData>
