<?xml version="1.0" encoding="UTF-8"?>
<!--oriflamms data file-->
<OriData>
    <validation>
        <v id="pc_inscriptions_5905" ok="2" left="0" right="0" imgsig=""/>
        <v id="pc_inscriptions_5884" ok="2" left="0" right="0" imgsig=""/>
        <v id="w_inscriptions_5899" ok="2" left="0" right="0" imgsig=""/>
        <v id="w_inscriptions_5877" ok="2" left="0" right="0" imgsig=""/>
        <v id="pc_inscriptions_5878" ok="2" left="0" right="0" imgsig=""/>
        <v id="pc_inscriptions_5903" ok="2" left="0" right="0" imgsig=""/>
        <v id="pc_inscriptions_5882" ok="2" left="0" right="0" imgsig=""/>
        <v id="w_inscriptions_5912" ok="2" left="0" right="0" imgsig=""/>
        <v id="w_inscriptions_5879" ok="2" left="0" right="0" imgsig=""/>
        <v id="pc_inscriptions_5880" ok="2" left="0" right="0" imgsig=""/>
        <v id="w_inscriptions_5881" ok="2" left="0" right="0" imgsig=""/>
        <v id="pc_inscriptions_5939" ok="2" left="0" right="0" imgsig=""/>
        <v id="w_inscriptions_5883" ok="2" left="0" right="0" imgsig=""/>
        <v id="w_inscriptions_5885" ok="2" left="0" right="0" imgsig=""/>
        <v id="pc_inscriptions_5907" ok="2" left="0" right="0" imgsig=""/>
        <v id="pc_inscriptions_5886" ok="2" left="0" right="0" imgsig=""/>
        <v id="w_inscriptions_5887" ok="2" left="0" right="0" imgsig=""/>
        <v id="pc_inscriptions_5909" ok="2" left="0" right="0" imgsig=""/>
        <v id="pc_inscriptions_5888" ok="2" left="0" right="0" imgsig=""/>
        <v id="pc_inscriptions_5890" ok="2" left="0" right="0" imgsig=""/>
        <v id="w_inscriptions_5889" ok="2" left="0" right="0" imgsig=""/>
        <v id="w_inscriptions_5891" ok="2" left="0" right="0" imgsig=""/>
        <v id="pc_inscriptions_5924" ok="2" left="0" right="0" imgsig=""/>
        <v id="w_inscriptions_5917" ok="2" left="0" right="0" imgsig=""/>
        <v id="w_inscriptions_5892" ok="2" left="0" right="0" imgsig=""/>
        <v id="pc_inscriptions_5930" ok="2" left="0" right="0" imgsig=""/>
        <v id="w_inscriptions_5921" ok="2" left="0" right="0" imgsig=""/>
        <v id="pc_inscriptions_5893" ok="2" left="0" right="0" imgsig=""/>
        <v id="pc_inscriptions_5922" ok="2" left="0" right="0" imgsig=""/>
        <v id="w_inscriptions_5894" ok="2" left="0" right="0" imgsig=""/>
        <v id="pc_inscriptions_5936" ok="2" left="0" right="0" imgsig=""/>
        <v id="w_inscriptions_5927" ok="2" left="0" right="0" imgsig=""/>
        <v id="pc_inscriptions_5895" ok="2" left="0" right="0" imgsig=""/>
        <v id="pc_inscriptions_5920" ok="2" left="0" right="0" imgsig=""/>
        <v id="w_inscriptions_5913" ok="2" left="0" right="0" imgsig=""/>
        <v id="w_inscriptions_5896" ok="2" left="0" right="0" imgsig=""/>
        <v id="pc_inscriptions_5934" ok="2" left="0" right="0" imgsig=""/>
        <v id="w_inscriptions_5925" ok="2" left="0" right="0" imgsig=""/>
        <v id="pc_inscriptions_5897" ok="2" left="0" right="0" imgsig=""/>
        <v id="w_inscriptions_5898" ok="2" left="0" right="0" imgsig=""/>
        <v id="w_inscriptions_5900" ok="2" left="0" right="0" imgsig=""/>
        <v id="w_inscriptions_5901" ok="2" left="0" right="0" imgsig=""/>
        <v id="w_inscriptions_5902" ok="2" left="0" right="0" imgsig=""/>
        <v id="w_inscriptions_5904" ok="2" left="0" right="0" imgsig=""/>
        <v id="w_inscriptions_5906" ok="2" left="0" right="0" imgsig=""/>
        <v id="w_inscriptions_5908" ok="2" left="0" right="0" imgsig=""/>
        <v id="w_inscriptions_5910" ok="2" left="0" right="0" imgsig=""/>
        <v id="pc_inscriptions_5911" ok="2" left="0" right="0" imgsig=""/>
        <v id="pc_inscriptions_5914" ok="2" left="0" right="0" imgsig=""/>
        <v id="pc_inscriptions_5926" ok="2" left="0" right="0" imgsig=""/>
        <v id="w_inscriptions_5915" ok="2" left="0" right="0" imgsig=""/>
        <v id="pc_inscriptions_5916" ok="2" left="0" right="0" imgsig=""/>
        <v id="pc_inscriptions_5918" ok="2" left="0" right="0" imgsig=""/>
        <v id="w_inscriptions_5919" ok="2" left="0" right="0" imgsig=""/>
        <v id="pc_inscriptions_5932" ok="2" left="0" right="0" imgsig=""/>
        <v id="w_inscriptions_5923" ok="2" left="0" right="0" imgsig=""/>
        <v id="pc_inscriptions_5928" ok="2" left="0" right="0" imgsig=""/>
        <v id="w_inscriptions_5929" ok="2" left="0" right="0" imgsig=""/>
        <v id="w_inscriptions_5931" ok="2" left="0" right="0" imgsig=""/>
        <v id="w_inscriptions_5933" ok="2" left="0" right="0" imgsig=""/>
        <v id="w_inscriptions_5935" ok="2" left="0" right="0" imgsig=""/>
        <v id="w_inscriptions_5937" ok="2" left="0" right="0" imgsig=""/>
        <v id="w_inscriptions_5938" ok="2" left="0" right="0" imgsig=""/>
    </validation>
    <medlines>
        <column id="col_inscriptions_253_1">
            <GraphicalLine lh="43">
                <LinearInterpolation>
                    <Point2DDouble x="107" y="57"/>
                    <Point2DDouble x="210" y="57"/>
                    <Point2DDouble x="448" y="79"/>
                    <Point2DDouble x="518" y="73"/>
                    <Point2DDouble x="546" y="72"/>
                    <Point2DDouble x="574" y="72"/>
                    <Point2DDouble x="644" y="71"/>
                    <Point2DDouble x="672" y="72"/>
                    <Point2DDouble x="700" y="73"/>
                    <Point2DDouble x="770" y="84"/>
                    <Point2DDouble x="840" y="89"/>
                    <Point2DDouble x="868" y="90"/>
                    <Point2DDouble x="896" y="90"/>
                    <Point2DDouble x="966" y="91"/>
                    <Point2DDouble x="1064" y="92"/>
                    <Point2DDouble x="1238" y="100"/>
                </LinearInterpolation>
            </GraphicalLine>
            <GraphicalLine lh="43">
                <LinearInterpolation>
                    <Point2DDouble x="939" y="2617"/>
                    <Point2DDouble x="1036" y="2626"/>
                    <Point2DDouble x="1168" y="2626"/>
                </LinearInterpolation>
            </GraphicalLine>
            <GraphicalLine lh="43">
                <LinearInterpolation>
                    <Point2DDouble x="442" y="3028"/>
                    <Point2DDouble x="546" y="3028"/>
                    <Point2DDouble x="588" y="3029"/>
                    <Point2DDouble x="616" y="3030"/>
                    <Point2DDouble x="658" y="3031"/>
                    <Point2DDouble x="700" y="3032"/>
                    <Point2DDouble x="728" y="3033"/>
                    <Point2DDouble x="770" y="3034"/>
                    <Point2DDouble x="798" y="3035"/>
                    <Point2DDouble x="826" y="3036"/>
                    <Point2DDouble x="854" y="3037"/>
                    <Point2DDouble x="882" y="3038"/>
                    <Point2DDouble x="910" y="3040"/>
                    <Point2DDouble x="994" y="3045"/>
                    <Point2DDouble x="1059" y="3045"/>
                </LinearInterpolation>
            </GraphicalLine>
            <GraphicalLine lh="43">
                <LinearInterpolation>
                    <Point2DDouble x="184" y="3184"/>
                    <Point2DDouble x="378" y="3184"/>
                    <Point2DDouble x="476" y="3183"/>
                    <Point2DDouble x="504" y="3182"/>
                    <Point2DDouble x="532" y="3181"/>
                    <Point2DDouble x="756" y="3162"/>
                    <Point2DDouble x="812" y="3167"/>
                    <Point2DDouble x="840" y="3168"/>
                    <Point2DDouble x="868" y="3169"/>
                    <Point2DDouble x="896" y="3170"/>
                    <Point2DDouble x="924" y="3171"/>
                    <Point2DDouble x="952" y="3172"/>
                    <Point2DDouble x="980" y="3173"/>
                    <Point2DDouble x="1008" y="3174"/>
                    <Point2DDouble x="1036" y="3175"/>
                    <Point2DDouble x="1078" y="3177"/>
                    <Point2DDouble x="1106" y="3178"/>
                    <Point2DDouble x="1118" y="3178"/>
                </LinearInterpolation>
            </GraphicalLine>
        </column>
    </medlines>
    <lineLinks>
        <ll id="line_inscriptions_253_1_1" col="col_inscriptions_253_1" n="0"/>
        <ll id="line_inscriptions_253_1_1a" col="col_inscriptions_253_1" n="1"/>
        <ll id="line_inscriptions_253_1_1b" col="col_inscriptions_253_1" n="2"/>
        <ll id="line_inscriptions_253_1_1c" col="col_inscriptions_253_1" n="3"/>
    </lineLinks>
</OriData>
