<?xml version="1.0" encoding="UTF-8"?>
<!--oriflamms data file-->
<OriData>
    <validation>
        <v id="w_p_w_inscriptions_2610_1" ok="2" left="0" right="0" imgsig=""/>
        <v id="w_inscriptions_2604" ok="2" left="0" right="0" imgsig=""/>
        <v id="w_inscriptions_2606" ok="2" left="0" right="0" imgsig=""/>
        <v id="w_p_w_inscriptions_2605_1" ok="2" left="0" right="0" imgsig=""/>
        <v id="w_p_w_inscriptions_2605_2" ok="2" left="0" right="0" imgsig=""/>
        <v id="w_inscriptions_2607" ok="2" left="0" right="0" imgsig=""/>
        <v id="w_inscriptions_2608" ok="2" left="0" right="0" imgsig=""/>
        <v id="w_p_w_inscriptions_2609_1" ok="2" left="0" right="0" imgsig=""/>
        <v id="w_p_w_inscriptions_2609_2" ok="2" left="0" right="0" imgsig=""/>
        <v id="w_p_w_inscriptions_2610_2" ok="2" left="0" right="0" imgsig=""/>
        <v id="w_inscriptions_2611" ok="2" left="0" right="0" imgsig=""/>
        <v id="w_inscriptions_2612" ok="2" left="0" right="0" imgsig=""/>
        <v id="w_inscriptions_2618" ok="2" left="0" right="0" imgsig=""/>
        <v id="w_p_w_inscriptions_2613_1" ok="2" left="0" right="0" imgsig=""/>
        <v id="pc_inscriptions_2615" ok="2" left="0" right="0" imgsig=""/>
        <v id="w_p_w_inscriptions_2613_2" ok="2" left="0" right="0" imgsig=""/>
        <v id="w_inscriptions_2614" ok="2" left="0" right="0" imgsig=""/>
        <v id="w_inscriptions_2616" ok="2" left="0" right="0" imgsig=""/>
        <v id="w_inscriptions_2619" ok="2" left="0" right="0" imgsig=""/>
        <v id="pc_inscriptions_2617" ok="2" left="0" right="0" imgsig=""/>
        <v id="pc_inscriptions_2620" ok="2" left="0" right="0" imgsig=""/>
        <v id="w_inscriptions_2622" ok="2" left="0" right="0" imgsig=""/>
        <v id="w_p_w_inscriptions_2621_1" ok="2" left="0" right="0" imgsig=""/>
        <v id="w_p_w_inscriptions_2621_2" ok="2" left="0" right="0" imgsig=""/>
        <v id="w_inscriptions_2623" ok="2" left="0" right="0" imgsig=""/>
    </validation>
    <medlines>
        <column id="col_inscriptions_84_1">
            <GraphicalLine lh="24">
                <LinearInterpolation>
                    <Point2DDouble x="356" y="412"/>
                    <Point2DDouble x="550" y="412"/>
                    <Point2DDouble x="640" y="411"/>
                    <Point2DDouble x="1250" y="397"/>
                    <Point2DDouble x="1448" y="396"/>
                </LinearInterpolation>
            </GraphicalLine>
            <GraphicalLine lh="24">
                <LinearInterpolation>
                    <Point2DDouble x="495" y="1026"/>
                    <Point2DDouble x="560" y="1026"/>
                    <Point2DDouble x="760" y="1033"/>
                    <Point2DDouble x="780" y="1033"/>
                    <Point2DDouble x="820" y="1034"/>
                    <Point2DDouble x="870" y="1035"/>
                    <Point2DDouble x="2850" y="1027"/>
                    <Point2DDouble x="2870" y="1028"/>
                    <Point2DDouble x="2874" y="1028"/>
                </LinearInterpolation>
            </GraphicalLine>
            <GraphicalLine lh="24">
                <LinearInterpolation>
                    <Point2DDouble x="87" y="1622"/>
                    <Point2DDouble x="340" y="1622"/>
                    <Point2DDouble x="390" y="1623"/>
                    <Point2DDouble x="440" y="1624"/>
                    <Point2DDouble x="550" y="1625"/>
                    <Point2DDouble x="680" y="1626"/>
                    <Point2DDouble x="750" y="1627"/>
                    <Point2DDouble x="2050" y="1623"/>
                    <Point2DDouble x="2090" y="1624"/>
                    <Point2DDouble x="2120" y="1625"/>
                    <Point2DDouble x="2140" y="1626"/>
                    <Point2DDouble x="2170" y="1627"/>
                    <Point2DDouble x="2210" y="1628"/>
                    <Point2DDouble x="2280" y="1629"/>
                    <Point2DDouble x="2446" y="1630"/>
                </LinearInterpolation>
            </GraphicalLine>
            <GraphicalLine lh="24">
                <LinearInterpolation>
                    <Point2DDouble x="1118" y="1705"/>
                    <Point2DDouble x="1220" y="1705"/>
                    <Point2DDouble x="1290" y="1706"/>
                    <Point2DDouble x="1350" y="1707"/>
                    <Point2DDouble x="1390" y="1708"/>
                    <Point2DDouble x="1430" y="1709"/>
                    <Point2DDouble x="1470" y="1710"/>
                    <Point2DDouble x="1620" y="1711"/>
                    <Point2DDouble x="3400" y="1725"/>
                    <Point2DDouble x="3420" y="1724"/>
                    <Point2DDouble x="3450" y="1723"/>
                    <Point2DDouble x="3568" y="1722"/>
                </LinearInterpolation>
            </GraphicalLine>
            <GraphicalLine lh="24">
                <LinearInterpolation>
                    <Point2DDouble x="217" y="2585"/>
                    <Point2DDouble x="320" y="2585"/>
                    <Point2DDouble x="350" y="2586"/>
                    <Point2DDouble x="370" y="2587"/>
                    <Point2DDouble x="400" y="2588"/>
                    <Point2DDouble x="440" y="2589"/>
                    <Point2DDouble x="730" y="2590"/>
                    <Point2DDouble x="1390" y="2592"/>
                    <Point2DDouble x="1430" y="2593"/>
                    <Point2DDouble x="1470" y="2594"/>
                    <Point2DDouble x="1510" y="2595"/>
                    <Point2DDouble x="1570" y="2596"/>
                    <Point2DDouble x="1620" y="2595"/>
                    <Point2DDouble x="2090" y="2609"/>
                    <Point2DDouble x="2240" y="2610"/>
                    <Point2DDouble x="2340" y="2610"/>
                    <Point2DDouble x="2400" y="2611"/>
                    <Point2DDouble x="2450" y="2612"/>
                    <Point2DDouble x="2510" y="2613"/>
                    <Point2DDouble x="2605" y="2614"/>
                </LinearInterpolation>
            </GraphicalLine>
            <GraphicalLine lh="24">
                <LinearInterpolation>
                    <Point2DDouble x="1447" y="3267"/>
                    <Point2DDouble x="2070" y="3267"/>
                    <Point2DDouble x="2120" y="3266"/>
                    <Point2DDouble x="2140" y="3265"/>
                    <Point2DDouble x="2170" y="3264"/>
                    <Point2DDouble x="3204" y="3263"/>
                </LinearInterpolation>
            </GraphicalLine>
            <GraphicalLine lh="24">
                <LinearInterpolation>
                    <Point2DDouble x="1131" y="3415"/>
                    <Point2DDouble x="1250" y="3415"/>
                    <Point2DDouble x="1290" y="3414"/>
                    <Point2DDouble x="1310" y="3413"/>
                    <Point2DDouble x="1340" y="3412"/>
                    <Point2DDouble x="1360" y="3411"/>
                    <Point2DDouble x="1390" y="3410"/>
                    <Point2DDouble x="2920" y="3431"/>
                    <Point2DDouble x="2960" y="3431"/>
                    <Point2DDouble x="3120" y="3432"/>
                </LinearInterpolation>
            </GraphicalLine>
            <GraphicalLine lh="24">
                <LinearInterpolation>
                    <Point2DDouble x="1313" y="4162"/>
                    <Point2DDouble x="2193" y="4162"/>
                </LinearInterpolation>
            </GraphicalLine>
            <GraphicalLine lh="24">
                <LinearInterpolation>
                    <Point2DDouble x="507" y="4586"/>
                    <Point2DDouble x="1370" y="4586"/>
                    <Point2DDouble x="2400" y="4575"/>
                    <Point2DDouble x="2567" y="4575"/>
                </LinearInterpolation>
            </GraphicalLine>
            <GraphicalLine lh="24">
                <LinearInterpolation>
                    <Point2DDouble x="115" y="5147"/>
                    <Point2DDouble x="390" y="5147"/>
                    <Point2DDouble x="450" y="5146"/>
                    <Point2DDouble x="520" y="5145"/>
                    <Point2DDouble x="630" y="5146"/>
                    <Point2DDouble x="940" y="5130"/>
                    <Point2DDouble x="1220" y="5115"/>
                    <Point2DDouble x="1310" y="5115"/>
                    <Point2DDouble x="1920" y="5121"/>
                    <Point2DDouble x="1940" y="5120"/>
                    <Point2DDouble x="1970" y="5119"/>
                    <Point2DDouble x="2000" y="5118"/>
                    <Point2DDouble x="2030" y="5117"/>
                    <Point2DDouble x="2060" y="5116"/>
                    <Point2DDouble x="2090" y="5115"/>
                    <Point2DDouble x="2110" y="5113"/>
                    <Point2DDouble x="2410" y="5109"/>
                    <Point2DDouble x="2910" y="5134"/>
                    <Point2DDouble x="2960" y="5134"/>
                    <Point2DDouble x="2980" y="5135"/>
                    <Point2DDouble x="3000" y="5136"/>
                    <Point2DDouble x="3080" y="5142"/>
                    <Point2DDouble x="3110" y="5143"/>
                    <Point2DDouble x="3130" y="5144"/>
                    <Point2DDouble x="3400" y="5143"/>
                    <Point2DDouble x="3567" y="5143"/>
                </LinearInterpolation>
            </GraphicalLine>
        </column>
    </medlines>
    <lineLinks>
        <ll id="line_inscriptions_84_1_1" col="col_inscriptions_84_1" n="0"/>
        <ll id="line_inscriptions_84_1_9" col="col_inscriptions_84_1" n="8"/>
        <ll id="line_inscriptions_84_1_2" col="col_inscriptions_84_1" n="1"/>
        <ll id="line_inscriptions_84_1_3" col="col_inscriptions_84_1" n="2"/>
        <ll id="line_inscriptions_84_1_4" col="col_inscriptions_84_1" n="3"/>
        <ll id="line_inscriptions_84_1_5" col="col_inscriptions_84_1" n="4"/>
        <ll id="line_inscriptions_84_1_6" col="col_inscriptions_84_1" n="5"/>
        <ll id="line_inscriptions_84_1_7" col="col_inscriptions_84_1" n="6"/>
        <ll id="line_inscriptions_84_1_8" col="col_inscriptions_84_1" n="7"/>
        <ll id="line_inscriptions_84_1_10" col="col_inscriptions_84_1" n="9"/>
    </lineLinks>
</OriData>
